BeewiPy/BeewiPy.py
BeewiPy/__init__.py
BeewiPy-0.0.1.dist-info/LICENSE
BeewiPy-0.0.1.dist-info/METADATA
BeewiPy-0.0.1.dist-info/WHEEL
BeewiPy-0.0.1.dist-info/top_level.txt
BeewiPy-0.0.1.dist-info/RECORD
