Metadata-Version: 2.1
Name: BeewiPy
Version: 0.0.1
Summary: A python library to interact with Beewi SmartBulb
Home-page: https://github.com/delkk0/BeewiPy
Author: David Polo
Author-email: dpolot@gmail.com
License: UNKNOWN
Platform: UNKNOWN
Classifier: Programming Language :: Python :: 3
Classifier: License :: OSI Approved :: GNU General Public License v3 or later (GPLv3+)
Classifier: Operating System :: OS Independent
Classifier: Topic :: Home Automation
Requires-Python: >=3.3
